fbchat/__init__.py
fbchat/_client.py
fbchat/_common.py
fbchat/_exception.py
fbchat/_fix_module_metadata.py
fbchat/_graphql.py
fbchat/_listen.py
fbchat/_session.py
fbchat/_util.py
fbchat/_events/__init__.py
fbchat/_events/_client_payload.py
fbchat/_events/_common.py
fbchat/_events/_delta_class.py
fbchat/_events/_delta_type.py
fbchat/_models/__init__.py
fbchat/_models/_attachment.py
fbchat/_models/_common.py
fbchat/_models/_file.py
fbchat/_models/_location.py
fbchat/_models/_message.py
fbchat/_models/_plan.py
fbchat/_models/_poll.py
fbchat/_models/_quick_reply.py
fbchat/_models/_sticker.py
fbchat/_threads/__init__.py
fbchat/_threads/_abc.py
fbchat/_threads/_group.py
fbchat/_threads/_page.py
fbchat/_threads/_user.py
fbchat_asyncio-0.6.21.dist-info/LICENSE
fbchat_asyncio-0.6.21.dist-info/METADATA
fbchat_asyncio-0.6.21.dist-info/WHEEL
fbchat_asyncio-0.6.21.dist-info/top_level.txt
fbchat_asyncio-0.6.21.dist-info/RECORD
